Workbook

Sheet Raw_Data_HUL
A1: Hindustan Unilever Ltd — Raw Financial Data (Ind AS), FY2021-FY2025
A2: Source: Company annual reports / consolidated filings (BSE/NSE) — Rs in Crores, fiscal year ended 31 March
A4: Line Item | B4: FY2021 | C4: FY2022 | D4: FY2023 | E4: FY2024 | F4: FY2025
A6: INCOME STATEMENT
A7: Revenue | B7: 47028 | C7: 52446 | D7: 60580 | E7: 61896 | F7: 61328
A8: Operating Profit | B8: 11626 | C8: 12857 | D8: 14147 | E8: 14659 | F8: 14698
A9: Net Profit | B9: 7999 | C9: 8892 | D9: 10143 | E9: 10282 | F9: 10671
A11: BALANCE SHEET
A12: Inventory | B12: 3579 | C12: 4096 | D12: 4251 | E12: 4022 | F12: 4415
A13: Total Current Assets | B13: 14217 | C13: 15522 | D13: 16998 | E13: 21324 | F13: 22051
A14: Total Assets | B14: 68740 | C14: 70506 | D14: 73077 | E14: 78489 | F14: 79863
A15: Total Current Liabilities | B15: 11103 | C15: 11280 | D15: 12028 | E15: 12879 | F15: 16537
A16: Total Liabilities (excl. equity) | B16: 21066 | C16: 21445 | D16: 22773 | E16: 27271 | F16: 30461
A17: Total Shareholders' Equity | B17: 47674 | C17: 49061 | D17: 50304 | E17: 51218 | F17: 49402
A19: CASH FLOW STATEMENT
A20: Operating Cash Flow | B20: 9163 | C20: 9048 | D20: 9991 | E20: 15469 | F20: 11886
A21: Free Cash Flow | B21: 5097 | C21: 7995 | D21: 8980 | E21: 14012 | F21: 10624
A23: Note: Total Liabilities (excl. equity) = Total Assets - Total Shareholders' Equity, for internal balance-sheet consistency across aggregator sources.
A24: Inventory valuation: HUL follows Ind AS 2, which permits FIFO or weighted-average cost; LIFO is prohibited under Ind AS.

Sheet Raw_Data_PG
A1: Procter & Gamble Co. — Raw Financial Data (US GAAP), FY2021-FY2025
A2: Source: P&G Form 10-K filings, SEC EDGAR (CIK 0000080424) — $ in Millions, fiscal year ended 30 June
A4: Line Item | B4: FY2021 | C4: FY2022 | D4: FY2023 | E4: FY2024 | F4: FY2025
A6: INCOME STATEMENT
A7: Revenue | B7: 76118 | C7: 80187 | D7: 82006 | E7: 84039 | F7: 84284
A8: Gross Profit | B8: 39010 | C8: 38030 | D8: 39246 | E8: 43191 | F8: 43120
A9: Operating Income | B9: 18000 | C9: 17800 | D9: 18100 | E9: 18500 | F9: 20500
A10: Net Income | B10: 14306 | C10: 14742 | D10: 14653 | E10: 14879 | F10: 15974
A12: BALANCE SHEET
A13: Inventory | B13: 5983 | C13: 6924 | D13: 7073 | E13: 7016 | F13: 7551
A14: Total Current Assets | B14: 23091 | C14: 21653 | D14: 22648 | E14: 24709 | F14: 25392
A15: Total Assets | B15: 119307 | C15: 117208 | D15: 120829 | E15: 122370 | F15: 125231
A16: Total Current Liabilities | B16: 33132 | C16: 33081 | D16: 35756 | E16: 33627 | F16: 36058
A17: Total Liabilities (excl. equity) | B17: 72653 | C17: 70354 | D17: 73764 | E17: 71811 | F17: 72946
A18: Total Shareholders' Equity | B18: 46654 | C18: 46854 | D18: 47065 | E18: 50559 | F18: 52284
A20: CASH FLOW STATEMENT
A21: Operating Cash Flow | B21: 18371 | C21: 16723 | D21: 16848 | E21: 19846 | F21: 17817
A22: Free Cash Flow | B22: 15584 | C22: 13567 | D22: 13786 | E22: 16524 | F22: 14044
A24: Note: Operating Income figures are from P&G's official Annual Report Financial Highlights (rounded to nearest $0.1B).
A25: Inventory valuation: P&G's 10-K states product-related inventories are primarily FIFO, with minor amounts (certain cosmetics/commodities) on LIFO. Spare parts use average-cost.

Sheet Ratios_Comparison
A1: US GAAP vs Ind AS — Ratio Comparison: Hindustan Unilever vs Procter & Gamble
A2: Ratios computed independently within each company's native currency/standard — cross-company values compare shape, not absolute scale.
A4: Ratio | B4: HUL FY2021 | C4: HUL FY2022 | D4: HUL FY2023 | E4: HUL FY2024 | F4: HUL FY2025 | G4: P&G FY2021 | H4: P&G FY2022 | I4: P&G FY2023 | J4: P&G FY2024 | K4: P&G FY2025
A6: LIQUIDITY
A7: Current Ratio | B7: =Raw_Data_HUL!B13/Raw_Data_HUL!B15 -> 1.2804647 | C7: =Raw_Data_HUL!C13/Raw_Data_HUL!C15 -> 1.3760638 | D7: =Raw_Data_HUL!D13/Raw_Data_HUL!D15 -> 1.4132025 | E7: =Raw_Data_HUL!E13/Raw_Data_HUL!E15 -> 1.6557186 | F7: =Raw_Data_HUL!F13/Raw_Data_HUL!F15 -> 1.3334341 | G7: =Raw_Data_PG!B14/Raw_Data_PG!B16 -> 0.69693951 | H7: =Raw_Data_PG!C14/Raw_Data_PG!C16 -> 0.6545449 | I7: =Raw_Data_PG!D14/Raw_Data_PG!D16 -> 0.63340418 | J7: =Raw_Data_PG!E14/Raw_Data_PG!E16 -> 0.73479644 | K7: =Raw_Data_PG!F14/Raw_Data_PG!F16 -> 0.70419879
A9: PROFITABILITY
A10: Operating Margin | B10: =Raw_Data_HUL!B8/Raw_Data_HUL!B7 -> 0.24721443 | C10: =Raw_Data_HUL!C8/Raw_Data_HUL!C7 -> 0.24514739 | D10: =Raw_Data_HUL!D8/Raw_Data_HUL!D7 -> 0.23352592 | E10: =Raw_Data_HUL!E8/Raw_Data_HUL!E7 -> 0.23683275 | F10: =Raw_Data_HUL!F8/Raw_Data_HUL!F7 -> 0.23966214 | G10: =Raw_Data_PG!B9/Raw_Data_PG!B7 -> 0.23647495 | H10: =Raw_Data_PG!C9/Raw_Data_PG!C7 -> 0.22198112 | I10: =Raw_Data_PG!D9/Raw_Data_PG!D7 -> 0.22071556 | J10: =Raw_Data_PG!E9/Raw_Data_PG!E7 -> 0.22013589 | K10: =Raw_Data_PG!F9/Raw_Data_PG!F7 -> 0.24322529
A11: Net Margin | B11: =Raw_Data_HUL!B9/Raw_Data_HUL!B7 -> 0.17009016 | C11: =Raw_Data_HUL!C9/Raw_Data_HUL!C7 -> 0.16954582 | D11: =Raw_Data_HUL!D9/Raw_Data_HUL!D7 -> 0.1674315 | E11: =Raw_Data_HUL!E9/Raw_Data_HUL!E7 -> 0.16611736 | F11: =Raw_Data_HUL!F9/Raw_Data_HUL!F7 -> 0.17399883 | G11: =Raw_Data_PG!B10/Raw_Data_PG!B7 -> 0.18794503 | H11: =Raw_Data_PG!C10/Raw_Data_PG!C7 -> 0.18384526 | I11: =Raw_Data_PG!D10/Raw_Data_PG!D7 -> 0.17868205 | J11: =Raw_Data_PG!E10/Raw_Data_PG!E7 -> 0.17704875 | K11: =Raw_Data_PG!F10/Raw_Data_PG!F7 -> 0.18952589
A12: Return on Assets (ROA) | B12: =Raw_Data_HUL!B9/Raw_Data_HUL!B14 -> 0.11636602 | C12: =Raw_Data_HUL!C9/Raw_Data_HUL!C14 -> 0.12611693 | D12: =Raw_Data_HUL!D9/Raw_Data_HUL!D14 -> 0.1387988 | E12: =Raw_Data_HUL!E9/Raw_Data_HUL!E14 -> 0.13099925 | F12: =Raw_Data_HUL!F9/Raw_Data_HUL!F14 -> 0.13361632 | G12: =Raw_Data_PG!B10/Raw_Data_PG!B15 -> 0.11990914 | H12: =Raw_Data_PG!C10/Raw_Data_PG!C15 -> 0.1257764 | I12: =Raw_Data_PG!D10/Raw_Data_PG!D15 -> 0.12127056 | J12: =Raw_Data_PG!E10/Raw_Data_PG!E15 -> 0.12159026 | K12: =Raw_Data_PG!F10/Raw_Data_PG!F15 -> 0.12755628
A13: Return on Equity (ROE) | B13: =Raw_Data_HUL!B9/Raw_Data_HUL!B17 -> 0.16778538 | C13: =Raw_Data_HUL!C9/Raw_Data_HUL!C17 -> 0.18124376 | D13: =Raw_Data_HUL!D9/Raw_Data_HUL!D17 -> 0.20163406 | E13: =Raw_Data_HUL!E9/Raw_Data_HUL!E17 -> 0.20074974 | F13: =Raw_Data_HUL!F9/Raw_Data_HUL!F17 -> 0.2160034 | G13: =Raw_Data_PG!B10/Raw_Data_PG!B18 -> 0.30664037 | H13: =Raw_Data_PG!C10/Raw_Data_PG!C18 -> 0.31463696 | I13: =Raw_Data_PG!D10/Raw_Data_PG!D18 -> 0.31133539 | J13: =Raw_Data_PG!E10/Raw_Data_PG!E18 -> 0.29428984 | K13: =Raw_Data_PG!F10/Raw_Data_PG!F18 -> 0.30552368
A15: LEVERAGE / SOLVENCY
A16: Debt-to-Equity (Total Liabilities / Equity) | B16: =Raw_Data_HUL!B16/Raw_Data_HUL!B17 -> 0.44187608 | C16: =Raw_Data_HUL!C16/Raw_Data_HUL!C17 -> 0.43710891 | D16: =Raw_Data_HUL!D16/Raw_Data_HUL!D17 -> 0.45270754 | E16: =Raw_Data_HUL!E16/Raw_Data_HUL!E17 -> 0.53244953 | F16: =Raw_Data_HUL!F16/Raw_Data_HUL!F17 -> 0.61659447 | G16: =Raw_Data_PG!B17/Raw_Data_PG!B18 -> 1.5572727 | H16: =Raw_Data_PG!C17/Raw_Data_PG!C18 -> 1.501558 | I16: =Raw_Data_PG!D17/Raw_Data_PG!D18 -> 1.5672793 | J16: =Raw_Data_PG!E17/Raw_Data_PG!E18 -> 1.4203406 | K16: =Raw_Data_PG!F17/Raw_Data_PG!F18 -> 1.3951878
A17: Equity Ratio (Equity / Total Assets) | B17: =Raw_Data_HUL!B17/Raw_Data_HUL!B14 -> 0.69354088 | C17: =Raw_Data_HUL!C17/Raw_Data_HUL!C14 -> 0.69584149 | D17: =Raw_Data_HUL!D17/Raw_Data_HUL!D14 -> 0.6883698 | E17: =Raw_Data_HUL!E17/Raw_Data_HUL!E14 -> 0.65255004 | F17: =Raw_Data_HUL!F17/Raw_Data_HUL!F14 -> 0.61858433 | G17: =Raw_Data_PG!B18/Raw_Data_PG!B15 -> 0.3910416 | H17: =Raw_Data_PG!C18/Raw_Data_PG!C15 -> 0.39975087 | I17: =Raw_Data_PG!D18/Raw_Data_PG!D15 -> 0.38951742 | J17: =Raw_Data_PG!E18/Raw_Data_PG!E15 -> 0.41316499 | K17: =Raw_Data_PG!F18/Raw_Data_PG!F15 -> 0.41750046
A19: EFFICIENCY
A20: Asset Turnover (Revenue / Total Assets) | B20: =Raw_Data_HUL!B7/Raw_Data_HUL!B14 -> 0.68414315 | C20: =Raw_Data_HUL!C7/Raw_Data_HUL!C14 -> 0.74385159 | D20: =Raw_Data_HUL!D7/Raw_Data_HUL!D14 -> 0.8289886 | E20: =Raw_Data_HUL!E7/Raw_Data_HUL!E14 -> 0.78859458 | F20: =Raw_Data_HUL!F7/Raw_Data_HUL!F14 -> 0.76791505 | G20: =Raw_Data_PG!B7/Raw_Data_PG!B15 -> 0.63800112 | H20: =Raw_Data_PG!C7/Raw_Data_PG!C15 -> 0.68414272 | I20: =Raw_Data_PG!D7/Raw_Data_PG!D15 -> 0.67869468 | J20: =Raw_Data_PG!E7/Raw_Data_PG!E15 -> 0.68676146 | K20: =Raw_Data_PG!F7/Raw_Data_PG!F15 -> 0.67302824
A22: CASH FLOW
A23: Free Cash Flow Margin (FCF / Revenue) | B23: =Raw_Data_HUL!B21/Raw_Data_HUL!B7 -> 0.10838224 | C23: =Raw_Data_HUL!C21/Raw_Data_HUL!C7 -> 0.15244251 | D23: =Raw_Data_HUL!D21/Raw_Data_HUL!D7 -> 0.14823374 | E23: =Raw_Data_HUL!E21/Raw_Data_HUL!E7 -> 0.22637973 | F23: =Raw_Data_HUL!F21/Raw_Data_HUL!F7 -> 0.17323245 | G23: =Raw_Data_PG!B22/Raw_Data_PG!B7 -> 0.20473475 | H23: =Raw_Data_PG!C22/Raw_Data_PG!C7 -> 0.16919201 | I23: =Raw_Data_PG!D22/Raw_Data_PG!D7 -> 0.16810965 | J23: =Raw_Data_PG!E22/Raw_Data_PG!E7 -> 0.196623 | K23: =Raw_Data_PG!F22/Raw_Data_PG!F7 -> 0.16662712
A24: Operating Cash Flow Ratio (OCF / Current Liabilities) | B24: =Raw_Data_HUL!B20/Raw_Data_HUL!B15 -> 0.82527245 | C24: =Raw_Data_HUL!C20/Raw_Data_HUL!C15 -> 0.80212766 | D24: =Raw_Data_HUL!D20/Raw_Data_HUL!D15 -> 0.83064516 | E24: =Raw_Data_HUL!E20/Raw_Data_HUL!E15 -> 1.2011026 | F24: =Raw_Data_HUL!F20/Raw_Data_HUL!F15 -> 0.71875189 | G24: =Raw_Data_PG!B21/Raw_Data_PG!B16 -> 0.55447905 | H24: =Raw_Data_PG!C21/Raw_Data_PG!C16 -> 0.50551676 | I24: =Raw_Data_PG!D21/Raw_Data_PG!D16 -> 0.47119365 | J24: =Raw_Data_PG!E21/Raw_Data_PG!E16 -> 0.59018051 | K24: =Raw_Data_PG!F21/Raw_Data_PG!F16 -> 0.49412058
A26: All ratios calculated directly from Raw_Data_HUL and Raw_Data_PG — update figures there and these recalculate automatically.

Sheet Standards_Differences
A1: US GAAP vs Ind AS — Key Accounting Standards Differences (FMCG Context)
A2: Qualitative reference table — supports interpretation of the ratio comparison, not a line-by-line restatement.
A4: Topic | B4: US GAAP (P&G) | C4: Ind AS (HUL) | D4: Practical Impact
A5: Revenue Recognition | B5: ASC 606: revenue recognized at a single point in time when control transfers; trade/volume discounts and returns recorded as reduction of sales. | C5: Ind AS 115: substantially converged with ASC 606 — revenue recognized when control transfers; discounts/rebates also net against revenue. | D5: Largely converged post-2018 (ASC 606 / Ind AS 115 both IFRS-15-based) — minimal practical divergence for FMCG revenue timing.
A6: Inventory Valuation | B6: ASC 330: lower of cost or market (or NRV); FIFO, LIFO, or average cost all permitted. P&G's 10-K confirms primarily FIFO, with minor LIFO for select items. | C6: Ind AS 2: lower of cost and net realizable value; FIFO or weighted-average permitted. LIFO is explicitly prohibited. | D6: P&G's own disclosed practice (mostly FIFO) means real-world divergence from HUL is smaller than the standards permit in theory.
A7: Lease Accounting | B7: ASC 842: lessee recognizes right-of-use asset and lease liability for most leases (operating and finance) on balance sheet. | C7: Ind AS 116: same core model as ASC 842 — right-of-use asset and lease liability recognized for nearly all leases. | D7: Both standards converged around 2019; minor differences remain in short-term/low-value lease exemption thresholds and discount rate guidance.
A8: Property, Plant & Equipment | B8: ASC 360: PP&E carried at historical cost less accumulated depreciation; revaluation to fair value is NOT permitted. | C8: Ind AS 16: allows a choice between the cost model and the revaluation model (fair value with periodic revaluation). | D8: If HUL elected revaluation for any asset class, its PP&E carrying values and depreciation charge would not be directly comparable to P&G's cost-only figures without restatement.
A9: Goodwill Treatment | B9: ASC 350: goodwill is not amortized; tested for impairment at least annually. | C9: Ind AS 103 / Ind AS 36: goodwill also not amortized under current Ind AS (aligned with IFRS 3); tested for impairment annually. | D9: Converged since Ind AS adoption — both companies expense goodwill only through impairment charges, not systematic amortization.
A11: Sources: P&G Form 10-K (SEC EDGAR); HUL Annual Reports; ICAI Ind AS standards text; FASB ASC codification.
